tianya/__init__.py
tianya/example.py
tianya-0.0.1.dist-info/LICENSE
tianya-0.0.1.dist-info/METADATA
tianya-0.0.1.dist-info/WHEEL
tianya-0.0.1.dist-info/top_level.txt
tianya-0.0.1.dist-info/RECORD
