Metadata-Version: 2.1
Name: tianya
Version: 0.0.1
Summary: example package
Author: Author
Author-email: linmi21st520@gmail.com
Requires-Python: >=3.6
License-File: LICENSE
